pack64.py
pack64-2.0.2.dist-info/METADATA
pack64-2.0.2.dist-info/WHEEL
pack64-2.0.2.dist-info/top_level.txt
pack64-2.0.2.dist-info/RECORD
