Metadata-Version: 2.1
Name: pack64
Version: 2.0.2
Summary: A library for representing floating point vectors in a compact, base64-like format
Home-page: http://github.com/LuminosoInsight/pack64
Maintainer: Luminoso Technologies, Inc.
Maintainer-email: info@luminoso.com
License: MIT
Platform: any
Requires-Dist: numpy (>=1.9.0)
